lens/__init__.py
lens/app.py
lens/utils.py
hcai_lens-1.0.4.dist-info/METADATA
hcai_lens-1.0.4.dist-info/WHEEL
hcai_lens-1.0.4.dist-info/entry_points.txt
hcai_lens-1.0.4.dist-info/top_level.txt
hcai_lens-1.0.4.dist-info/RECORD
