Metadata-Version: 2.1
Name: hcai-lens
Version: 1.0.4
Summary: LENS is a lightweight webserver designed to use Large Language Models as tool for data exploration in human interactions.
Author-email: Dominik Schiller <dominik.schiller@uni-a.de>
Project-URL: Repository, https://github.com/hcmlab/lens
Keywords: LENS,DISCOVER,LLM,machine learning
Classifier: Development Status :: 4 - Beta
Classifier: Programming Language :: Python
Classifier: Intended Audience :: Developers
Classifier: Topic :: Software Development :: Build Tools
Classifier: License :: OSI Approved :: MIT License
Classifier: Programming Language :: Python :: 3.9
Classifier: Programming Language :: Python :: 3.10
Classifier: Programming Language :: Python :: 3 :: Only
Requires-Python: >=3.9
Requires-Dist: flask==3.0.0
Requires-Dist: flask-caching
Requires-Dist: waitress
Requires-Dist: python-dotenv
Requires-Dist: psutil
Requires-Dist: litellm==1.46.8
